easy_web_app-0.1.4.dist-info/DESCRIPTION.rst
easy_web_app-0.1.4.dist-info/METADATA
easy_web_app-0.1.4.dist-info/RECORD
easy_web_app-0.1.4.dist-info/WHEEL
easy_web_app-0.1.4.dist-info/metadata.json
easy_web_app-0.1.4.dist-info/top_level.txt
easywebapp/__init__.py
easywebapp/page_layout.py
easywebapp/webapp.py
