Metadata-Version: 2.0
Name: easy-web-app
Version: 0.1.4
Summary: Create web applications easily by defining them in JSON format.
Home-page: https://github.com/ma-ha/easy-py-web-app
Author: ma-ha
Author-email: ma@mh-svr.de
License: MIT
Keywords: GUI web app browser AJAX easy portal REST RESTful web service form table I/O content serverless API centric
Platform: UNKNOWN
Classifier: Development Status :: 2 - Pre-Alpha
Classifier: Programming Language :: Python :: 2
Classifier: Topic :: Internet :: WWW/HTTP
Classifier: License :: OSI Approved :: MIT License
Classifier: Operating System :: OS Independent
Requires-Dist: WebTest
Requires-Dist: nose
Requires-Dist: web.py
